__init__.py
drug_resolver/__init__.py
drug_resolver/core.py
drug_resolver/core_test.py
drug_resolver/requests_wrapper.py
drug_resolver/utils.py
drug_resolver-0.0.5.dist-info/METADATA
drug_resolver-0.0.5.dist-info/WHEEL
drug_resolver-0.0.5.dist-info/top_level.txt
drug_resolver-0.0.5.dist-info/RECORD
