Metadata-Version: 2.2
Name: drug_resolver
Version: 0.0.5
Summary: A tool to resolve messy drug names in biomedical datasets to standard identifiers
Author-email: Jeff Quinn <quinnj2@mskcc.org>
Maintainer-email: Jeff Quinn <quinnj2@mskcc.org>
Project-URL: Homepage, https://github.com/tansey-lab/drug-resolver
Project-URL: Source, https://github.com/tansey-lab/drug-resolver
Classifier: Development Status :: 5 - Production/Stable
Classifier: Programming Language :: Python :: 3 :: Only
Requires-Python: >=3.10
Requires-Dist: requests-cache<1,>=0.9.7
Requires-Dist: requests<3,>=2.28.1
Requires-Dist: xmltodict==0.13.0
Requires-Dist: rdkit>=2022.9.4
Provides-Extra: dev
Requires-Dist: check-manifest; extra == "dev"
Provides-Extra: test
Requires-Dist: pytest; extra == "test"
Requires-Dist: pytest-mock; extra == "test"
Requires-Dist: tox; extra == "test"
